http_client_sync.py
http_client_sync-0.1.1.dist-info/WHEEL
http_client_sync-0.1.1.dist-info/METADATA
http_client_sync-0.1.1.dist-info/RECORD
